pm_rank/__init__.py
pm_rank/crawler/__init__.py
pm_rank/crawler/scrape_gjo_predictions_data.py
pm_rank/crawler/scrape_gjo_problem_data.py
pm_rank/data/__init__.py
pm_rank/data/base.py
pm_rank/data/loaders.py
pm_rank/data/utils.py
pm_rank/model/__init__.py
pm_rank/model/average_return.py
pm_rank/model/bradley_terry.py
pm_rank/model/calibration.py
pm_rank/model/scoring_rule.py
pm_rank/model/utils.py
pm_rank/model/irt/__init__.py
pm_rank/model/irt/_dataset.py
pm_rank/model/irt/_irt_utils.py
pm_rank/model/irt/_pyro_models.py
pm_rank/nightly/algo.py
pm_rank/nightly/bootstrap.py
pm_rank/nightly/data.py
pm_rank/nightly/misc.py
pm_rank/nightly/plot.py
pm_rank/nightly/plot_timestamp.py
pm_rank/nightly/test_algo.py
pm_rank/nightly/test_bootstrap.py
pm_rank/nightly/test_calibration.py
pm_rank/nightly/utils.py
pm_rank/plotting/__init__.py
pm_rank/plotting/plot_correlations_multiple_metrics.py
pm_rank/plotting/plot_crra_risks_curves.py
pm_rank/plotting/plot_reliability_diagram.py
pm_rank-0.2.32.dist-info/METADATA
pm_rank-0.2.32.dist-info/WHEEL
pm_rank-0.2.32.dist-info/top_level.txt
pm_rank-0.2.32.dist-info/RECORD
