Metadata-Version: 2.4
Name: pm_rank
Version: 0.2.32
Summary: A toolkit for scoring and ranking prediction market forecasters.
Author-email: Sida Li <listar2000@uchicago.edu>
Requires-Python: >=3.8
Requires-Dist: numpy
Requires-Dist: matplotlib
Requires-Dist: seaborn
Requires-Dist: pandas
Requires-Dist: tqdm
Provides-Extra: docs
Requires-Dist: sphinx; extra == "docs"
Requires-Dist: sphinxawesome-theme; extra == "docs"
Requires-Dist: sphinx-math-dollar; extra == "docs"
Requires-Dist: myst-parser; extra == "docs"
Requires-Dist: sphinx-autoapi; extra == "docs"
Provides-Extra: full
Requires-Dist: pyro-ppl; extra == "full"
Requires-Dist: sphinx; extra == "full"
Requires-Dist: sphinxawesome-theme; extra == "full"
Requires-Dist: sphinx-math-dollar; extra == "full"
Requires-Dist: myst-parser; extra == "full"
